{
  "InputArguments": {
    "key": "xxxxxxxxxxxxxxxxxxxxxx",
    "id": "xxxxxx"
  },
  "VesselNames": [
    " 72 Flybridge",
    " Apolline ",
    "tractor"
  ],
  "Types": [
    "Sail",
    "Power"
  ],
  "Categories": {
    "Power": {
      "Aft Cabin": "Aft Cabin",
      "Airboat": "Airboat",
      "Aluminum Fish Boats": "Aluminum Fish Boats",
      "Antique and Classics": "Antique and Classics",
      "Barge": "Barge",
      "Bass Boats": "Bass Boats",
      "Bay Boats": "Bay Boats",
      "Bowrider": "Bowrider",
      "Catamaran": "Catamaran",
      "Center Cockpit": "Center Cockpit",
      "Center Consoles": "Center Consoles",
      "Commercial Boats": "Commercial Boats",
      "Convertible Boats": "Convertible Boats",
      "Cruise Ship": "Cruise Ship",
      "Cruiser-Racer": "Cruiser-Racer",
      "Cruisers": "Cruisers",
      "Cuddy Cabin": "Cuddy Cabin",
      "Deck Boats": "Deck Boats",
      "Dive Boat": "Dive Boat",
      "Downeast": "Downeast",
      "Dual Console": "Dual Console",
      "Express Cruiser": "Express Cruiser",
      "Flats Boats": "Flats Boats",
      "Flybridge": "Flybridge",
      "Freshwater Fishing": "Freshwater Fishing",
      "House Boats": "House Boats",
      "Inflatables": "Inflatables",
      "Jet Boats": "Jet Boats",
      "Lobster Boat": "Lobster Boat",
      "Motor Yachts": "Motor Yachts",
      "Motorsailers": "Motorsailers",
      "Other": "Other",
      "Passenger": "Passenger",
      "Personal Watercraft": "Personal Watercraft",
      "Pilothouse": "Pilothouse",
      "Pontoon Boats": "Pontoon Boats",
      "Power Catamarans": "Power Catamarans",
      "Racing-High Performance": "Racing-High Performance",
      "Rigid Inflatable Boats": "Rigid Inflatable Boats",
      "Runabouts": "Runabouts",
      "Saltwater Fishing": "Saltwater Fishing",
      "Ski & Fish": "Ski & Fish",
      "Ski-Wakeboard Boats": "Ski-Wakeboard Boats",
      "Skiff": "Skiff",
      "Sport Fishing": "Sport Fishing",
      "Sports Cruiser": "Sports Cruiser",
      "Tender": "Tender",
      "Trawlers": "Trawlers",
      "Troller": "Troller",
      "Tug": "Tug",
      "Unspecified": "Unspecified",
      "Utility Boats": "Utility Boats",
      "Walkarounds": "Walkarounds"
    },
    "Sail": {
      "Antique and Classics": "Antique and Classics",
      "Beach Catamarans": "Beach Catamarans",
      "Catamaran": "Catamaran",
      "Center Cockpit": "Center Cockpit",
      "Cruiser-Racer": "Cruiser-Racer",
      "Cruisers": "Cruisers",
      "Cutter": "Cutter",
      "Daysailers": "Daysailers",
      "Deck Saloon": "Deck Saloon",
      "Dinghies": "Dinghies",
      "Ketch": "Ketch",
      "Motorsailers": "Motorsailers",
      "Multi-Hulls": "Multi-Hulls",
      "Other": "Other",
      "Pilothouse": "Pilothouse",
      "Power Catamarans": "Power Catamarans",
      "Racing Sailboat": "Racing Sailboat",
      "Schooner": "Schooner",
      "Sloop": "Sloop",
      "Trimaran": "Trimaran",
      "Unspecified": "Unspecified",
      "Yawl": "Yawl"
    }
  },
  "Brands": [
    "3D Tender",
    "7oceans",
    "AB",
    "AB Inflatables",
    "ACM"
  ],
  "Events": [
    {
      "EventID": 600006,
      "EventName": "Stuart Boat Show 2018"
    },
    {
      "EventID": 600010,
      "EventName": "Key West Run"
    },
    {
      "EventID": 600024,
      "EventName": "St. Petersburg Power & Sailboat Show"
    },
    {
      "EventID": 600064,
      "EventName": "St. Petersburg Power & Sailboat Show"
    },
    {
      "EventID": 600066,
      "EventName": "2019 Fort Myers Boat Show"
    }
  ],
  "City": [
    "",
    " Antalya",
    " Boca Raton",
    " Fernandina Beach",
    " Fort Lauderdale",
    " Fort Myers",
    " Greenwich",
    " Miami",
    " Newport",
    " Oyster Bay",
    " Riviera Nayarit  ",
    " Stuart",
    "ARNOLD",
    "Abacos",
    "Acapulco",
    "Afton",
    "Alameda",
    "Alexander City",
    "Alexandria Bay",
    "Algonac",
    "Alligator Point",
    "Alpena",
    "stamford,ct"
  ],
  "State": [
    {
      "value": "Queensland",
      "key": "Queensland"
    }
  ],
  "VesselIds": [
    2766875,
    2763846
  ],
  "Users": [
    {
      "key": 80787,
      "value": "Emma Ross"
    },
    {
      "key": 80112,
      "value": "Garrett Schwartz"
    },
    {
      "key": 82173,
      "value": "Jonne Houwing"
    },
    {
      "key": 80009,
      "value": "Paul Flannery"
    },
    {
      "key": 80022,
      "value": "Shay Loudenslager"
    },
    {
      "key": 80483,
      "value": "Test Broker"
    }
  ],
  "VesselStatus": {
    "Draft": "Draft",
    "On": "On",
    "Suspend": "Suspend",
    "Sold": "Sold",
    "Under Contract": "Under Contract",
    "Private": "Private"
  },
  "PrivateNewsCategories": [
    {
      "key": 2,
      "value": "Company"
    }
  ],
  "PrivateNewsTags": [
    {
      "key": 2,
      "value": "Marketing"
    },
    {
      "key": 1,
      "value": "News"
    }
  ],
  "BrokerageId": 40000030,
  "ResultCount": 6850,
  "DisplayLengthMinFeet": 7,
  "DisplayLengthMaxFeet": 579,
  "DisplayLengthMinMeters": 2,
  "DisplayLengthMaxMeters": 177,
  "LOAMinimumFeet": 0,
  "LOAMaximumFeet": 579,
  "LOAMinimumMeter": 0,
  "LOAMaximumMeter": 177,
  "PriceMinimumUSD": "0",
  "PriceMaximumUSD": "111111111",
  "PriceMinumumEuro": "0",
  "PriceMaximumEuro": "99544778",
  "PriceMinumumCAD": "0",
  "PriceMaximumCAD": "148930555",
  "PriceMinumumGBP": "0",
  "PriceMaximumGBP": "87372111",
  "MinimumYear": 38,
  "MaximumYear": 2023,
  "MetaData": {
    "RequestTimestamp": "2019-11-24T20:28:17.000000Z",
    "ResponseTimestamp": "2019-11-24T20:28:17.000000Z",
    "ResponseGenerationTimeSeconds": 0.0088419914245605,
    "ResponseSizeKB": 134.873046875
  }
}